{
  "scraped_at": "2026-07-17T10:01:28.474Z",
  "scraped_at_et": "7/17/2026, 6:01:28 AM",
  "total_listings": 11,
  "listings": [
    {
      "title": "Rolex Datejust 36 Stainless Steel White Roman Dial 126200",
      "price": "$9,000",
      "status": "In stock",
      "listed_date": ""
    },
    {
      "title": "Rolex GMT-Master II Rose Gold “Root Beer” Black Dial 126715CHNR",
      "price": "$41,200",
      "status": "In stock",
      "listed_date": ""
    },
    {
      "title": "Rolex Daytona Yellow Gold Green Dial 116508",
      "price": "$72,400",
      "status": "In stock",
      "listed_date": ""
    },
    {
      "title": "Panerai Submersible S Brabus Carbotech Skeletonized Black and Green Dial PAM01283",
      "price": "$44,000",
      "status": "In stock",
      "listed_date": ""
    },
    {
      "title": "Panerai Submersible NavySeals Stainless Steel/Ceramic Grey Dial PAM01402",
      "price": "$70,000",
      "status": "In stock",
      "listed_date": ""
    },
    {
      "title": "Panerai Radiomir Bronze Green Ombre Dial PAM 00760",
      "price": "$13,500",
      "status": "In stock",
      "listed_date": ""
    },
    {
      "title": "Rolex Daytona Stainless Steel Ceramic Bezel White Dial 116500LN",
      "price": "$34,550",
      "status": "In stock",
      "listed_date": ""
    },
    {
      "title": "Cartier Calibre De Cartier Diver Stainless Steel Blue Roman Dial WSCA0010",
      "price": "$5,050",
      "status": "Sold",
      "listed_date": ""
    },
    {
      "title": "Rolex Sky-Dweller Stainless Steel and White Gold Green Stick Dial 336934",
      "price": "$29,000",
      "status": "Active",
      "listed_date": ""
    },
    {
      "title": "Rolex Daytona Cosmograph Yellow Gold “Pickachu” Dial 126508",
      "price": "$72,250",
      "status": "Active",
      "listed_date": ""
    },
    {
      "title": "Patek Philippe Annual Calendar Flyback Chronograph Rose Gold Blue Dial 5905R-010",
      "price": "$66,550",
      "status": "In stock",
      "listed_date": ""
    }
  ]
}